zeroframe_ws_client/__init__.py
zeroframe_ws_client-1.2.0.dist-info/LICENSE
zeroframe_ws_client-1.2.0.dist-info/METADATA
zeroframe_ws_client-1.2.0.dist-info/WHEEL
zeroframe_ws_client-1.2.0.dist-info/top_level.txt
zeroframe_ws_client-1.2.0.dist-info/RECORD
