Metadata-Version: 2.1
Name: zeroframe-ws-client
Version: 1.2.0
Summary: ZeroFrame WebSocket API for Python
Home-page: https://github.com/filips123/ZeroFramePy/
Author: Filip Š
Author-email: projects@filips.si
License: MIT
Keywords: zeronet,zeroframe,websocket,library,p2p,decentralized
Platform: UNKNOWN
Classifier: Development Status :: 5 - Production/Stable
Classifier: Intended Audience :: Developers
Classifier: License :: OSI Approved :: MIT License
Classifier: Programming Language :: Python :: 3
Classifier: Topic :: Communications
Classifier: Topic :: Internet
Classifier: Topic :: Software Development :: Libraries
Classifier: Topic :: Utilities
Requires-Python: >= 3.5
Requires-Dist: websocket-client (<0.57.0,>=0.56.0)
Provides-Extra: lint
Requires-Dist: pylint ; extra == 'lint'
